__init__.py
__main__.py
classroom.py
course.py
department.py
person.py
student.py
teacher.py
school_management_leo-1.0.0.dist-info/METADATA
school_management_leo-1.0.0.dist-info/WHEEL
school_management_leo-1.0.0.dist-info/entry_points.txt
school_management_leo-1.0.0.dist-info/top_level.txt
school_management_leo-1.0.0.dist-info/RECORD
